{
  "article": {
    "id": 360032765411,
    "url": "https://hatenablogmedia.zendesk.com/api/v2/help_center/ja/articles/360032765411.json",
    "html_url": "https://hatenablogmedia.zendesk.com/hc/ja/articles/360032765411",
    "author_id": 378867417791,
    "comments_disabled": false,
    "draft": false,
    "promoted": false,
    "position": 3,
    "vote_sum": 3,
    "vote_count": 3,
    "section_id": 360006001411,
    "created_at": "2019-08-21T05:17:04Z",
    "updated_at": "2025-01-08T03:12:32Z",
    "name": "独自ドメインを設定する",
    "title": "独自ドメインを設定する",
    "source_locale": "ja",
    "locale": "ja",
    "outdated": false,
    "outdated_locales": [],
    "edited_at": "2025-01-08T03:00:01Z",
    "user_segment_id": null,
    "permission_group_id": 972311,
    "content_tag_ids": [],
    "label_names": [],
    "body": "<p class=\"undefined\">独自ドメインの設定は全プラン共通のため、下記のはてなブログのヘルプをご参照ください。</p>\n<ul>\n<li><a href=\"https://help.hatenablog.com/entry/customdomain\">はてなブログを独自ドメインで利用する - はてなブログ ヘルプ</a></li>\n</ul>\n<div class=\"section\"> </div>",
    "user_segment_ids": []
  }
}
